aiv_lib/__init__.py
aiv_lib/aws_polly_util.py
aiv_lib/aws_s3_util.py
aiv_lib/cloud_gcp_functions.py
aiv_lib/cloud_gcp_storage.py
aiv_lib/util_ConfigManager.py
aiv_lib/util_DatabaseUtil.py
aiv_lib/util_FireStoreHelper_social_media.py
aiv_lib/util_Movies.py
aiv_lib/util_ai_service.py
aiv_lib/util_audio_elevenlabs.py
aiv_lib/util_audio_service.py
aiv_lib/util_bing_search.py
aiv_lib/util_caption_creator.py
aiv_lib/util_caption_writer.py
aiv_lib/util_common_operation.py
aiv_lib/util_diffusion_prompts.py
aiv_lib/util_gif_creator_tenor.py
aiv_lib/util_google_api.py
aiv_lib/util_google_cloud_storage.py
aiv_lib/util_image_ai.py
aiv_lib/util_insta_server_client.py
aiv_lib/util_instagram_interface.py
aiv_lib/util_key_value_store.py
aiv_lib/util_pexel_video_downloader.py
aiv_lib/util_social_media_video.py
aiv_lib/util_upload_social_media_artifact.py
aiv_lib/util_video_creator.py
aiv_lib-0.0.1.dist-info/METADATA
aiv_lib-0.0.1.dist-info/WHEEL
aiv_lib-0.0.1.dist-info/RECORD
